robustml/__init__.py
robustml/attack.py
robustml/dataset.py
robustml/evaluate.py
robustml/model.py
robustml/provider.py
robustml/threat_model.py
robustml-0.0.3.dist-info/LICENSE.txt
robustml-0.0.3.dist-info/METADATA
robustml-0.0.3.dist-info/WHEEL
robustml-0.0.3.dist-info/top_level.txt
robustml-0.0.3.dist-info/RECORD
