Metadata-Version: 2.1
Name: robustml
Version: 0.0.3
Summary: Robust ML API
Home-page: https://github.com/robust-ml/robust-ml
Author: Anish Athalye
Author-email: me@anishathalye.com
License: MIT
Platform: UNKNOWN
Requires-Dist: numpy (<2,>=1)
Requires-Dist: Pillow (<6,>=5)
